embroidery.py
embroidery-1.0.2a0.dist-info/licenses/LICENSE.md
embroidery-1.0.2a0.dist-info/METADATA
embroidery-1.0.2a0.dist-info/WHEEL
embroidery-1.0.2a0.dist-info/top_level.txt
embroidery-1.0.2a0.dist-info/RECORD
