Metadata-Version: 2.4
Name: embroidery
Version: 1.0.2a0
Summary: A basic library for creating and altering machine embroidery files with Python.
Author: Josh Varga, Robin Swift
License-Expression: Zlib
Project-URL: Homepage, https://www.libembroidery.org
Project-URL: Source, https://github.com/embroidermodder/libembroidery
Project-URL: Issues, https://github.com/embroidermodder/libembroidery/issues
Classifier: Operating System :: OS Independent
Classifier: Development Status :: 3 - Alpha
Requires-Python: >=3.7
License-File: LICENSE.md
Dynamic: license-file
